model/__init__.py
model/deepsurrogate.py
model/ml_model.py
model/parameters.py
DeepSurrogatepin-1.7.dist-info/LICENSE.txt
DeepSurrogatepin-1.7.dist-info/METADATA
DeepSurrogatepin-1.7.dist-info/WHEEL
DeepSurrogatepin-1.7.dist-info/top_level.txt
DeepSurrogatepin-1.7.dist-info/RECORD
