Metadata-Version: 2.1
Name: DeepSurrogatepin
Version: 1.7
Summary: Deep surrogate model for the probability of informed trading model
Home-page: https://github.com/GuillaumePv/pin_surrogate_model
Author: Guillaume Pavé
Author-email: guillaumepave@gmail.com
License: MIT
Keywords: Machine learning, market microstructure
Classifier: Development Status :: 3 - Alpha
Classifier: Intended Audience :: Developers
Classifier: Topic :: Software Development :: Build Tools
Classifier: License :: OSI Approved :: MIT License
Classifier: Programming Language :: Python :: 3.4
Classifier: Programming Language :: Python :: 3.5
Classifier: Programming Language :: Python :: 3.6
Classifier: Programming Language :: Python :: 3.7
Classifier: Programming Language :: Python :: 3.8
License-File: LICENSE.txt
Requires-Dist: numpy
Requires-Dist: pandas
Requires-Dist: tensorflow
Requires-Dist: tqdm
Requires-Dist: tensorflow-probability
